genometools/__init__.py
genometools/cli.py
genometools/gtf.py
genometools/basic/__init__.py
genometools/basic/gene_set.py
genometools/basic/gene_set_collection.py
genometools/basic/species.py
genometools/data/RdBu_r_colormap.tsv
genometools/data/gcloud/pipelines/fastqc.sh
genometools/data/gcloud/pipelines/sra_download_paired-end.sh
genometools/data/gcloud/pipelines/trim_fastq.sh
genometools/data/gcloud/pipelines/STAR/generate_index.sh
genometools/data/gcloud/pipelines/STAR/map_paired-end.sh
genometools/data/gcloud/pipelines/STAR/map_single-end.sh
genometools/data/gcloud/scripts/delete_instance.sh
genometools/data/gcloud/scripts/install_crcmod.sh
genometools/data/gcloud/scripts/install_docker.sh
genometools/data/gcloud/scripts/install_gcc.sh
genometools/data/gcloud/scripts/install_python.sh
genometools/data/tests/human_ensembl88_1000.gtf.gz
genometools/ebi/__init__.py
genometools/ebi/uniprot_goa.py
genometools/enrichment/__init__.py
genometools/enrichment/analysis.py
genometools/enrichment/result.py
genometools/ensembl/__init__.py
genometools/ensembl/annotations.py
genometools/ensembl/cdna.py
genometools/ensembl/dna.py
genometools/ensembl/filter_fasta.py
genometools/ensembl/species.py
genometools/ensembl/util.py
genometools/ensembl/cli/__init__.py
genometools/ensembl/cli/extract_protein_coding_exon_annotations.py
genometools/ensembl/cli/extract_protein_coding_gene_ids.py
genometools/ensembl/cli/extract_protein_coding_genes.py
genometools/ensembl/cli/util.py
genometools/expression/__init__.py
genometools/expression/cluster.py
genometools/expression/convert_entrez2gene.py
genometools/expression/filter.py
genometools/expression/gene.py
genometools/expression/gene_table.py
genometools/expression/matrix.py
genometools/expression/normalize.py
genometools/expression/profile.py
genometools/expression/visualize/__init__.py
genometools/expression/visualize/annotation.py
genometools/expression/visualize/corr_heatmap.py
genometools-0.4.1.dist-info/DESCRIPTION.rst
genometools-0.4.1.dist-info/METADATA
genometools-0.4.1.dist-info/RECORD
genometools-0.4.1.dist-info/WHEEL
genometools-0.4.1.dist-info/entry_points.txt
genometools-0.4.1.dist-info/metadata.json
genometools-0.4.1.dist-info/top_level.txt
