Metadata-Version: 2.0
Name: genometools
Version: 0.4.1
Summary: GenomeTools: A Python Toolkit for Working with Genomic Data.
Home-page: https://github.com/flo-compbio/genometools
Author: Florian Wagner
Author-email: florian.wagner@duke.edu
License: GPLv3
Keywords: genome genes tools analysis expression sequencing
Platform: UNKNOWN
Classifier: Development Status :: 4 - Beta
Classifier: Intended Audience :: Developers
Classifier: Intended Audience :: Science/Research
Classifier: Topic :: Scientific/Engineering :: Bio-Informatics
Classifier: License :: OSI Approved :: GNU General Public License v3 (GPLv3)
Classifier: Programming Language :: Python :: 3.5
Classifier: Programming Language :: Python :: 3.6
Requires-Dist: six (<2,>=1.5.2)
Requires-Dist: future (<1,>=0.15.2)
Requires-Dist: requests (<3,>=2.9.1)
Requires-Dist: unicodecsv (<1,>=0.14.1)
Requires-Dist: xmltodict (<1,>=0.10.1)
Requires-Dist: ftputil (<4,>=3.3.1)
Requires-Dist: numpy (<2,>=1.8)
Requires-Dist: pandas (<1,>=0.20.1)
Requires-Dist: xlmhg (<3,>=2.4.9)
Requires-Dist: google-cloud-storage (>=0.23.1)
Requires-Dist: oauth2client (<5,>=4)
Requires-Dist: jinja2 (<3,>=2.9.5)
Requires-Dist: biopython (>=1.69)
Requires-Dist: sortedcontainers (<2,>=1.5.7)
Requires-Dist: scipy (<2,>=1)
Requires-Dist: plotly (<3,>=2)
Provides-Extra: docs
Requires-Dist: sphinx; extra == 'docs'
Requires-Dist: sphinx-rtd-theme; extra == 'docs'
Requires-Dist: sphinx-argparse; extra == 'docs'
Requires-Dist: mock; extra == 'docs'
Provides-Extra: tests
Requires-Dist: pytest (<4,>=2.8.5); extra == 'tests'
Requires-Dist: pytest-cov (<3,>=2.2.1); extra == 'tests'
